{"sq":[
{"id":"1","title":"贪财之徒","type":[1,2],"desc":"青龙帮帮主得知掌门想知道十四天书的消息，向掌门开出了条件，掌门可先前去跟他谈一谈","place":"m1-1-2","npc":"n003","bossword":"我这里有你想要的消息，但是，你想让我开口是要付出点代价的。","need1":["r005-10002"],"need1desc":"给他钱财","need2":"0","need2desc":"教训他","mutex1":"0","mutex2":"0","reward1":["r002-1000","0-0","0-0"],"reward2":["r002-1000","0-0","0-0"]},
{"id":"2","title":"十四天书","type":[2],"desc":"传言青龙帮最近一直在打探十四天书的消息，掌门可以去找他们打听打听关于十四天书的事情","place":"m1-1-1","npc":"n012","bossword":"来者何人！想活命的赶紧离开青龙帮！","need1":["0-0"],"need1desc":"0","need2":"0","need2desc":"硬闯","mutex1":"0","mutex2":"2-2","reward1":["r002-1000","0-0","0-0"],"reward2":["r002-1000","0-0","0-0"]},
{"id":"3","title":"房间","type":[1],"desc":"阿朵根据阿里的高科技ask的感觉阿莱克光剑啊塑料袋可根据阿斯顿感","place":"m1-1-2","npc":"n012","bossword":"我这里有你想要的消息，但是，你想让我开口是要付出点代价的。","need1":["r005-1000"],"need1desc":"给他钱财","need2":"0","need2desc":"教训他","mutex1":"0","mutex2":"0","reward1":["r002-1000","0-0","0-0"],"reward2":["0-0","0-0","0-0"]}
]}